{
	"hero": {
		"heroId": "145",
		"name": "虚空之女",
		"alias": "Kaisa",
		"title": "卡莎",
		"roles": [
			"marksman"
		],
		"shortBio": "在孩童时期就被虚空夺走的卡莎，凭着纯粹的固执和意志力活了下来。她的历练让她成为了一位夺命的猎手，或者也有人会称她为黑暗未来的使者。她与一副有生命的虚空生物甲壳形成了一种不得安宁的共生状态，而很快她就将面临一个重大的抉择，究竟是原谅那些称她为怪物的凡人并协力抵御压境的黑暗……还是干脆忘记，放任虚空吞噬这个已将她抛弃的世界。",
		"camp": "",
		"attack": "8",
		"defense": "5",
		"magic": "3",
		"difficulty": "6",
		"hp": "571.0000",
		"hpperlevel": "86.0000",
		"mp": "344.8800",
		"mpperlevel": "38.0000",
		"movespeed": "335.0000",
		"armor": "28.0000",
		"armorperlevel": "3.0000",
		"spellblock": "30.0000",
		"spellblockperlevel": "0.5000",
		"attackrange": "525.0000",
		"hpregen": "3.5000",
		"hpregenperlevel": "0.5500",
		"mpregen": "8.2000",
		"mpregenperlevel": "0.4500",
		"crit": "0.0000",
		"critperlevel": "0.0000",
		"attackdamage": "59.0000",
		"attackdamageperlevel": "1.7000",
		"attackspeed": "0.6440",
		"attackspeedperlevel": "1.8000",
		"allytips": [
			"-尝试抓住对方落单的输出，并用艾卡西亚暴雨来将其轰杀。\n与你的队友一起发动你的终极技能，并利用你的被动来充分输出伤害。\n确保购买那些能够至少进化你1到2个技能的装备。"
		],
		"enemytips": [
			"-卡莎非常善于带走落单的敌人。要对付她就得保持抱团。\n卡莎很容易就会在对抗法师和超远程输出时陷入射程劣势。\n请时刻保证自己已在盲区布置了守卫，这样一来就能看到卡莎的到来了。"
		],
		"heroVideoPath": "",
		"isWeekFree": "0",
		"damageType": "kMixed",
		"style": "2",
		"difficultyL": "2",
		"damage": "3",
		"durability": "1",
		"crowdControl": "0",
		"mobility": "3",
		"utility": "1",
		"selectAudio": "https://game.gtimg.cn/images/lol/act/img/vo/choose/145.ogg",
		"banAudio": "https://game.gtimg.cn/images/lol/act/img/vo/ban/145.ogg"
	},
	"skins": [
		{
			"skinId": "145000",
			"heroId": "145",
			"heroName": "虚空之女",
			"heroTitle": "卡莎",
			"name": "虚空之女",
			"chromas": "0",
			"chromasBelongId": "0",
			"isBase": "1",
			"emblemsName": "base",
			"description": "",
			"mainImg": "https://game.gtimg.cn/images/lol/act/img/skin/big145000.jpg",
			"iconImg": "https://game.gtimg.cn/images/lol/act/img/skin/small145000.jpg",
			"loadingImg": "https://game.gtimg.cn/images/lol/act/img/skinloading/145000.jpg",
			"videoImg": "https://game.gtimg.cn/images/lol/act/img/skinvideo/sp145000.jpg",
			"sourceImg": "https://game.gtimg.cn/images/lol/act/img/guidetop/guide145000.jpg",
			"vedioPath": "",
			"suitType": "",
			"publishTime": "",
			"chromaImg": ""
		},
		{
			"skinId": "145001",
			"heroId": "145",
			"heroName": "虚空之女",
			"heroTitle": "卡莎",
			"name": "弹幕天使 卡莎",
			"chromas": "0",
			"chromasBelongId": "0",
			"isBase": "0",
			"emblemsName": "common",
			"description": "卡莎曾经是皇家太空军的一员，现在她是第一位驾驶实验型X01-蝴蝶号的驾驶员。通过她的首次试飞表明这套战斗机甲过于致命，然而在这一次试飞之后她就带着飞船逃跑了——成为了全宇宙最危险的杀手。",
			"mainImg": "https://game.gtimg.cn/images/lol/act/img/skin/big145001.jpg",
			"iconImg": "https://game.gtimg.cn/images/lol/act/img/skin/small145001.jpg",
			"loadingImg": "https://game.gtimg.cn/images/lol/act/img/skinloading/145001.jpg",
			"videoImg": "https://game.gtimg.cn/images/lol/act/img/skinvideo/sp145001.jpg",
			"sourceImg": "https://game.gtimg.cn/images/lol/act/img/guidetop/guide145001.jpg",
			"vedioPath": "",
			"suitType": "",
			"publishTime": "",
			"chromaImg": ""
		},
		{
			"skinId": "145002",
			"heroId": "145",
			"heroName": "虚空之女",
			"heroTitle": "卡莎",
			"name": "弹幕天使 卡莎 炽天使·圣洁",
			"chromas": "1",
			"chromasBelongId": "145001",
			"isBase": "0",
			"emblemsName": "",
			"description": "",
			"mainImg": "",
			"iconImg": "",
			"loadingImg": "",
			"videoImg": "",
			"sourceImg": "",
			"vedioPath": "",
			"suitType": "",
			"publishTime": "",
			"chromaImg": "https://game.gtimg.cn/images/lol/act/img/chromas/145/145002.png"
		},
		{
			"skinId": "145003",
			"heroId": "145",
			"heroName": "虚空之女",
			"heroTitle": "卡莎",
			"name": "弹幕天使 卡莎 炽天使·热忱",
			"chromas": "1",
			"chromasBelongId": "145001",
			"isBase": "0",
			"emblemsName": "",
			"description": "",
			"mainImg": "",
			"iconImg": "",
			"loadingImg": "",
			"videoImg": "",
			"sourceImg": "",
			"vedioPath": "",
			"suitType": "",
			"publishTime": "",
			"chromaImg": "https://game.gtimg.cn/images/lol/act/img/chromas/145/145003.png"
		},
		{
			"skinId": "145004",
			"heroId": "145",
			"heroName": "虚空之女",
			"heroTitle": "卡莎",
			"name": "弹幕天使 卡莎 炽天使·勇敢",
			"chromas": "1",
			"chromasBelongId": "145001",
			"isBase": "0",
			"emblemsName": "",
			"description": "",
			"mainImg": "",
			"iconImg": "",
			"loadingImg": "",
			"videoImg": "",
			"sourceImg": "",
			"vedioPath": "",
			"suitType": "",
			"publishTime": "",
			"chromaImg": "https://game.gtimg.cn/images/lol/act/img/chromas/145/145004.png"
		},
		{
			"skinId": "145005",
			"heroId": "145",
			"heroName": "虚空之女",
			"heroTitle": "卡莎",
			"name": "弹幕天使 卡莎 炽天使·敏锐",
			"chromas": "1",
			"chromasBelongId": "145001",
			"isBase": "0",
			"emblemsName": "",
			"description": "",
			"mainImg": "",
			"iconImg": "",
			"loadingImg": "",
			"videoImg": "",
			"sourceImg": "",
			"vedioPath": "",
			"suitType": "",
			"publishTime": "",
			"chromaImg": "https://game.gtimg.cn/images/lol/act/img/chromas/145/145005.png"
		},
		{
			"skinId": "145006",
			"heroId": "145",
			"heroName": "虚空之女",
			"heroTitle": "卡莎",
			"name": "弹幕天使 卡莎 炽天使·坚忍",
			"chromas": "1",
			"chromasBelongId": "145001",
			"isBase": "0",
			"emblemsName": "",
			"description": "",
			"mainImg": "",
			"iconImg": "",
			"loadingImg": "",
			"videoImg": "",
			"sourceImg": "",
			"vedioPath": "",
			"suitType": "",
			"publishTime": "",
			"chromaImg": "https://game.gtimg.cn/images/lol/act/img/chromas/145/145006.png"
		},
		{
			"skinId": "145007",
			"heroId": "145",
			"heroName": "虚空之女",
			"heroTitle": "卡莎",
			"name": "弹幕天使 卡莎 炽天使·威严",
			"chromas": "1",
			"chromasBelongId": "145001",
			"isBase": "0",
			"emblemsName": "",
			"description": "",
			"mainImg": "",
			"iconImg": "",
			"loadingImg": "",
			"videoImg": "",
			"sourceImg": "",
			"vedioPath": "",
			"suitType": "",
			"publishTime": "",
			"chromaImg": "https://game.gtimg.cn/images/lol/act/img/chromas/145/145007.png"
		},
		{
			"skinId": "145008",
			"heroId": "145",
			"heroName": "虚空之女",
			"heroTitle": "卡莎",
			"name": "弹幕天使 卡莎 炽天使·忠诚",
			"chromas": "1",
			"chromasBelongId": "145001",
			"isBase": "0",
			"emblemsName": "",
			"description": "",
			"mainImg": "",
			"iconImg": "",
			"loadingImg": "",
			"videoImg": "",
			"sourceImg": "",
			"vedioPath": "",
			"suitType": "",
			"publishTime": "",
			"chromaImg": "https://game.gtimg.cn/images/lol/act/img/chromas/145/145008.png"
		},
		{
			"skinId": "145009",
			"heroId": "145",
			"heroName": "虚空之女",
			"heroTitle": "卡莎",
			"name": "弹幕天使 卡莎 炽天使·公正",
			"chromas": "1",
			"chromasBelongId": "145001",
			"isBase": "0",
			"emblemsName": "",
			"description": "",
			"mainImg": "",
			"iconImg": "",
			"loadingImg": "",
			"videoImg": "",
			"sourceImg": "",
			"vedioPath": "",
			"suitType": "",
			"publishTime": "",
			"chromaImg": "https://game.gtimg.cn/images/lol/act/img/chromas/145/145009.png"
		},
		{
			"skinId": "145014",
			"heroId": "145",
			"heroName": "虚空之女",
			"heroTitle": "卡莎",
			"name": "K/DA 卡莎",
			"chromas": "0",
			"chromasBelongId": "0",
			"isBase": "0",
			"emblemsName": "common",
			"description": "卡莎是来自国外的天才，将独特的风格和声音带到了音乐产业。她已掌握了通过她的才艺来表达她自身，并跻身于全世界最具天赋的舞者之列——对K/DA的异类们来说是个完美的同类，因为她可以让她们的表现力更上一层楼。",
			"mainImg": "https://game.gtimg.cn/images/lol/act/img/skin/big145014.jpg",
			"iconImg": "https://game.gtimg.cn/images/lol/act/img/skin/small145014.jpg",
			"loadingImg": "https://game.gtimg.cn/images/lol/act/img/skinloading/145014.jpg",
			"videoImg": "https://game.gtimg.cn/images/lol/act/img/skinvideo/sp145014.jpg",
			"sourceImg": "https://game.gtimg.cn/images/lol/act/img/guidetop/guide145014.jpg",
			"vedioPath": "",
			"suitType": "",
			"publishTime": "",
			"chromaImg": ""
		},
		{
			"skinId": "145015",
			"heroId": "145",
			"heroName": "虚空之女",
			"heroTitle": "卡莎",
			"name": "K/DA 卡莎 至臻",
			"chromas": "0",
			"chromasBelongId": "0",
			"isBase": "0",
			"emblemsName": "Prestige",
			"description": "刚刚现身于年度流行音乐奖的K/DA卡莎，正穿着一件至臻奢华的全金服装——吸引着整个世界的目光。",
			"mainImg": "https://game.gtimg.cn/images/lol/act/img/skin/big145015.jpg",
			"iconImg": "https://game.gtimg.cn/images/lol/act/img/skin/small145015.jpg",
			"loadingImg": "https://game.gtimg.cn/images/lol/act/img/skinloading/145015.jpg",
			"videoImg": "https://game.gtimg.cn/images/lol/act/img/skinvideo/sp145015.jpg",
			"sourceImg": "https://game.gtimg.cn/images/lol/act/img/guidetop/guide145015.jpg",
			"vedioPath": "",
			"suitType": "",
			"publishTime": "",
			"chromaImg": ""
		},
		{
			"skinId": "145016",
			"heroId": "145",
			"heroName": "虚空之女",
			"heroTitle": "卡莎",
			"name": "iG 卡莎",
			"chromas": "0",
			"chromasBelongId": "0",
			"isBase": "0",
			"emblemsName": "Champion Limited",
			"description": "以此致敬JackeyLove在2018全球总决赛中使用卡莎的亮眼表现。",
			"mainImg": "https://game.gtimg.cn/images/lol/act/img/skin/big145016.jpg",
			"iconImg": "https://game.gtimg.cn/images/lol/act/img/skin/small145016.jpg",
			"loadingImg": "https://game.gtimg.cn/images/lol/act/img/skinloading/145016.jpg",
			"videoImg": "https://game.gtimg.cn/images/lol/act/img/skinvideo/sp145016.jpg",
			"sourceImg": "https://game.gtimg.cn/images/lol/act/img/guidetop/guide145016.jpg",
			"vedioPath": "",
			"suitType": "",
			"publishTime": "",
			"chromaImg": ""
		},
		{
			"skinId": "145017",
			"heroId": "145",
			"heroName": "虚空之女",
			"heroTitle": "卡莎",
			"name": "电玩女神 卡莎",
			"chromas": "0",
			"chromasBelongId": "0",
			"isBase": "0",
			"emblemsName": "common",
			"description": "卡莎是一名来自地狱多向射击游戏“像素虚空2”的赏金猎人和前任士兵。在战场BOSS们感染了她的游戏后，她被召回到电玩剧场。由于她在击杀那些拥有海量生命值的霸屏BOSS级怪物方面有着无与伦比的实力，因此入侵“像素虚空2”也许会成为一次严重的误算。",
			"mainImg": "https://game.gtimg.cn/images/lol/act/img/skin/big145017.jpg",
			"iconImg": "https://game.gtimg.cn/images/lol/act/img/skin/small145017.jpg",
			"loadingImg": "https://game.gtimg.cn/images/lol/act/img/skinloading/145017.jpg",
			"videoImg": "https://game.gtimg.cn/images/lol/act/img/skinvideo/sp145017.jpg",
			"sourceImg": "https://game.gtimg.cn/images/lol/act/img/guidetop/guide145017.jpg",
			"vedioPath": "",
			"suitType": "",
			"publishTime": "",
			"chromaImg": ""
		},
		{
			"skinId": "145018",
			"heroId": "145",
			"heroName": "虚空之女",
			"heroTitle": "卡莎",
			"name": "电玩女神 卡莎 K.O.",
			"chromas": "1",
			"chromasBelongId": "145017",
			"isBase": "0",
			"emblemsName": "",
			"description": "",
			"mainImg": "",
			"iconImg": "",
			"loadingImg": "",
			"videoImg": "",
			"sourceImg": "",
			"vedioPath": "",
			"suitType": "",
			"publishTime": "",
			"chromaImg": "https://game.gtimg.cn/images/lol/act/img/chromas/145/145018.png"
		},
		{
			"skinId": "145019",
			"heroId": "145",
			"heroName": "虚空之女",
			"heroTitle": "卡莎",
			"name": "电玩女神 卡莎 强袭丽影",
			"chromas": "1",
			"chromasBelongId": "145017",
			"isBase": "0",
			"emblemsName": "",
			"description": "",
			"mainImg": "",
			"iconImg": "",
			"loadingImg": "",
			"videoImg": "",
			"sourceImg": "",
			"vedioPath": "",
			"suitType": "",
			"publishTime": "",
			"chromaImg": "https://game.gtimg.cn/images/lol/act/img/chromas/145/145019.png"
		},
		{
			"skinId": "145020",
			"heroId": "145",
			"heroName": "虚空之女",
			"heroTitle": "卡莎",
			"name": "电玩女神 卡莎 华丽舞步",
			"chromas": "1",
			"chromasBelongId": "145017",
			"isBase": "0",
			"emblemsName": "",
			"description": "",
			"mainImg": "",
			"iconImg": "",
			"loadingImg": "",
			"videoImg": "",
			"sourceImg": "",
			"vedioPath": "",
			"suitType": "",
			"publishTime": "",
			"chromaImg": "https://game.gtimg.cn/images/lol/act/img/chromas/145/145020.png"
		},
		{
			"skinId": "145021",
			"heroId": "145",
			"heroName": "虚空之女",
			"heroTitle": "卡莎",
			"name": "电玩女神 卡莎 绚烂弹幕",
			"chromas": "1",
			"chromasBelongId": "145017",
			"isBase": "0",
			"emblemsName": "",
			"description": "",
			"mainImg": "",
			"iconImg": "",
			"loadingImg": "",
			"videoImg": "",
			"sourceImg": "",
			"vedioPath": "",
			"suitType": "",
			"publishTime": "",
			"chromaImg": "https://game.gtimg.cn/images/lol/act/img/chromas/145/145021.png"
		},
		{
			"skinId": "145022",
			"heroId": "145",
			"heroName": "虚空之女",
			"heroTitle": "卡莎",
			"name": "电玩女神 卡莎 钢铁天使",
			"chromas": "1",
			"chromasBelongId": "145017",
			"isBase": "0",
			"emblemsName": "",
			"description": "",
			"mainImg": "",
			"iconImg": "",
			"loadingImg": "",
			"videoImg": "",
			"sourceImg": "",
			"vedioPath": "",
			"suitType": "",
			"publishTime": "",
			"chromaImg": "https://game.gtimg.cn/images/lol/act/img/chromas/145/145022.png"
		},
		{
			"skinId": "145023",
			"heroId": "145",
			"heroName": "虚空之女",
			"heroTitle": "卡莎",
			"name": "电玩女神 卡莎 致命狙杀",
			"chromas": "1",
			"chromasBelongId": "145017",
			"isBase": "0",
			"emblemsName": "",
			"description": "",
			"mainImg": "",
			"iconImg": "",
			"loadingImg": "",
			"videoImg": "",
			"sourceImg": "",
			"vedioPath": "",
			"suitType": "",
			"publishTime": "",
			"chromaImg": "https://game.gtimg.cn/images/lol/act/img/chromas/145/145023.png"
		},
		{
			"skinId": "145024",
			"heroId": "145",
			"heroName": "虚空之女",
			"heroTitle": "卡莎",
			"name": "电玩女神 卡莎 极速融解",
			"chromas": "1",
			"chromasBelongId": "145017",
			"isBase": "0",
			"emblemsName": "",
			"description": "",
			"mainImg": "",
			"iconImg": "",
			"loadingImg": "",
			"videoImg": "",
			"sourceImg": "",
			"vedioPath": "",
			"suitType": "",
			"publishTime": "",
			"chromaImg": "https://game.gtimg.cn/images/lol/act/img/chromas/145/145024.png"
		},
		{
			"skinId": "145025",
			"heroId": "145",
			"heroName": "虚空之女",
			"heroTitle": "卡莎",
			"name": "电玩女神 卡莎 时光勇者",
			"chromas": "1",
			"chromasBelongId": "145017",
			"isBase": "0",
			"emblemsName": "",
			"description": "",
			"mainImg": "",
			"iconImg": "",
			"loadingImg": "",
			"videoImg": "",
			"sourceImg": "",
			"vedioPath": "",
			"suitType": "",
			"publishTime": "",
			"chromaImg": "https://game.gtimg.cn/images/lol/act/img/chromas/145/145025.png"
		}
	],
	"spells": [
		{
			"heroId": "145",
			"spellKey": "e",
			"name": "极限超载",
			"description": "卡莎暂时提升移动速度，随后提升攻击速度。<br><br>活体武器：这个技能得到升级，可短暂提供隐形效果。",
			"abilityIconPath": "https://game.gtimg.cn/images/lol/act/img/spell/KaisaE.png",
			"abilityVideoPath": "champion-abilities/0145/ability_0145_E1.webm",
			"dynamicDescription": "卡莎进行蓄力，短暂地增加移动速度，但期间不能攻击。蓄力结束后，卡莎会提高攻击速度，持续数秒。\r\n普通攻击可以降低极限超载的冷却时间。\r\n\r\n持续时长：4秒\r\n\r\n活体武器：\r\n当卡莎的属性获得了足够的额外攻击速度，她在极限超载蓄力过程中会进入潜行状态。\r\n\r\n【卢安娜的飓风】的箭矢不再为【极限超载】提供冷却缩减\r\n",
			"cost": [
				"30",
				"30",
				"30",
				"30",
				"30"
			],
			"costburn": "30",
			"cooldown": [
				"14",
				"14.5",
				"15",
				"15.5",
				"16"
			],
			"cooldownburn": "16/15.5/15/14.5/14",
			"range": [
				"1",
				"1",
				"1",
				"1",
				"1"
			]
		},
		{
			"heroId": "145",
			"spellKey": "passive",
			"name": "体表活肤",
			"description": "卡莎的普通攻击会叠加电浆，造成不断提升的额外魔法伤害。友军的定身效果也可以帮忙叠加电浆。此外，卡莎可通过购买装备来升级她的基础技能，让它们拥有更多强大的属性。",
			"abilityIconPath": "https://game.gtimg.cn/images/lol/act/img/passive/Kaisa_Passive.png",
			"abilityVideoPath": "champion-abilities/0145/ability_0145_P1.webm",
			"dynamicDescription": "",
			"cost": false,
			"costburn": "",
			"cooldown": false,
			"cooldownburn": "",
			"range": false
		},
		{
			"heroId": "145",
			"spellKey": "q",
			"name": "艾卡西亚暴雨",
			"description": "卡莎发射一大堆弹体来搜寻附近的目标。<br><br>活体武器：这个技能得到升级，可发射更多弹体。",
			"abilityIconPath": "https://game.gtimg.cn/images/lol/act/img/spell/KaisaQ.png",
			"abilityVideoPath": "champion-abilities/0145/ability_0145_Q1.webm",
			"dynamicDescription": "卡莎以扇形发射出多枚导弹攻击敌人。同一目标被多发导弹命中时受到的伤害会略微降低。\r\n\r\n活体武器：\r\n当卡莎的属性获得了足够的额外物理伤害，艾卡西亚暴雨发射的导弹数量会大幅增加。\r\n",
			"cost": [
				"55",
				"55",
				"55",
				"55",
				"55"
			],
			"costburn": "55",
			"cooldown": [
				"6",
				"6.5",
				"7",
				"7.5",
				"8"
			],
			"cooldownburn": "8/7.5/7/6.5/6",
			"range": [
				"600",
				"600",
				"600",
				"600",
				"600"
			]
		},
		{
			"heroId": "145",
			"spellKey": "r",
			"name": "猎手本能",
			"description": "卡莎突进到一个敌方英雄身边。",
			"abilityIconPath": "https://game.gtimg.cn/images/lol/act/img/spell/KaisaR.png",
			"abilityVideoPath": "champion-abilities/0145/ability_0145_R1.webm",
			"dynamicDescription": "卡莎以极高的速度，从很远的距离突进至身上有电浆效果的敌方英雄附近，并获得一个暂时性的伤害吸收护盾。\r\n",
			"cost": [
				"100",
				"100",
				"100"
			],
			"costburn": "100",
			"cooldown": [
				"70",
				"90",
				"110"
			],
			"cooldownburn": "110/90/70",
			"range": [
				"1500",
				"2000",
				"2500"
			]
		},
		{
			"heroId": "145",
			"spellKey": "w",
			"name": "虚空索敌",
			"description": "卡莎发射一束长程弹体，并用她的被动来标记敌人。<br><br>活体武器：这个技能得到升级，可施加更多被动标记并在命中英雄时减少冷却时间。",
			"abilityIconPath": "https://game.gtimg.cn/images/lol/act/img/spell/KaisaW.png",
			"abilityVideoPath": "champion-abilities/0145/ability_0145_W1.webm",
			"dynamicDescription": "卡莎射出一束虚空能量，暴露第一个命中的敌人的位置，造成魔法伤害，并叠加电浆效果。\r\n\r\n活体武器：\r\n当卡莎的属性获得了足够的额外法术强度，虚空索敌会造成更多的伤害，并在命中敌方英雄时降低此技能的冷却时间。",
			"cost": [
				"55",
				"60",
				"65",
				"70",
				"75"
			],
			"costburn": "55/60/65/70/75",
			"cooldown": [
				"14",
				"16",
				"18",
				"20",
				"22"
			],
			"cooldownburn": "22/20/18/16/14",
			"range": [
				"3000",
				"3000",
				"3000",
				"3000",
				"3000"
			]
		}
	],
	"version": "10.5",
	"fileName": "145.js",
	"fileTime": "2020-03-10 10:48:53"
}